compose/__init__.py
compose/args.py
compose/empty.py
compose/kwargs.py
compose/mkmeth.py
compose/structs.py
compose/templates.py
compose_struct-0.8.0.dist-info/LICENSE
compose_struct-0.8.0.dist-info/METADATA
compose_struct-0.8.0.dist-info/WHEEL
compose_struct-0.8.0.dist-info/top_level.txt
compose_struct-0.8.0.dist-info/RECORD
