Metadata-Version: 2.1
Name: compose-struct
Version: 0.8.0
Summary: yet another namedtuple alternative
Home-page: https://github.com/ninjaaron/compose-struct
License: UNKNOWN
Platform: UNKNOWN
Requires-Python: >=3.5
